funcli.py
funcli/__init__.py
funcli/_impl.py
funcli/py.typed
funcli-0.7.1.dist-info/LICENSE
funcli-0.7.1.dist-info/METADATA
funcli-0.7.1.dist-info/WHEEL
funcli-0.7.1.dist-info/top_level.txt
funcli-0.7.1.dist-info/RECORD
